nexusdata/__init__.py
nexusdata/client.py
nexusdata/lib/lib.dll
nexusdata/lib/lib.h
nexusdata/lib/lib.so
nexusdata/proto/qwdata_pb2.py
nexusdata/proto/qwdata_pb2_grpc.py
nexusdata-2.0.1.dist-info/LICENSE
nexusdata-2.0.1.dist-info/METADATA
nexusdata-2.0.1.dist-info/WHEEL
nexusdata-2.0.1.dist-info/top_level.txt
nexusdata-2.0.1.dist-info/RECORD
