Metadata-Version: 2.2
Name: nexusdata
Version: 2.0.1
Summary: Quantweb3 Data API for quants
Author-email: Scott Zhang <scott2011@qq.com>
License: MIT License
Project-URL: Homepage, https://quantweb3.ai
Classifier: Programming Language :: Python :: 3
Classifier: License :: OSI Approved :: MIT License
Classifier: Operating System :: OS Independent
Requires-Python: >=3.7
License-File: LICENSE
Requires-Dist: python-snappy>=0.7.2
Requires-Dist: grpcio>=1.64.1
Requires-Dist: pandas>=1.5.3
Requires-Dist: protobuf>=4.25.3
Requires-Dist: tqdm>=4.65.0
